soccer_xg/__init__.py
soccer_xg/api.py
soccer_xg/calibration.py
soccer_xg/features.py
soccer_xg/metrics.py
soccer_xg/ml/logreg.py
soccer_xg/ml/mlp.py
soccer_xg/ml/pipeline.py
soccer_xg/ml/preprocessing.py
soccer_xg/ml/tree_based_LR.py
soccer_xg/ml/xgboost.py
soccer_xg/models/openplay_logreg_advanced
soccer_xg/models/openplay_logreg_basic
soccer_xg/models/openplay_xgboost_advanced
soccer_xg/models/openplay_xgboost_basic
soccer_xg/utils.py
soccer_xg/visualisation.py
soccer_xg/xg.py
soccer_xg-0.0.1.dist-info/LICENSE
soccer_xg-0.0.1.dist-info/WHEEL
soccer_xg-0.0.1.dist-info/METADATA
soccer_xg-0.0.1.dist-info/RECORD
