Metadata-Version: 2.1
Name: soccer-xg
Version: 0.0.1
Summary: Train and analyse xG models on soccer event stream data
Home-page: https://pypi.org/project/soccer_xg
Keywords: expected goals,xG,Soccer,Football,event stream data,sports analytics,Statsbomb,Opta,Wyscout
Author: Pieter Robberechts
Author-email: pieter.robberechts@cs.kuleuven.be
Requires-Python: >=3.6.1,<4.0.0
Classifier: License :: OSI Approved :: Apache Software License
Classifier: Operating System :: OS Independent
Classifier: Programming Language :: Python :: 3
Classifier: Programming Language :: Python :: 3.7
Classifier: Programming Language :: Python :: 3.8
Provides-Extra: dask
Requires-Dist: asyncssh (>=2.2.1,<3.0.0); extra == "dask"
Requires-Dist: betacal (>=0.2.7,<0.3.0)
Requires-Dist: category_encoders (>=2.2.2,<3.0.0)
Requires-Dist: click (>=7.0,<8.0)
Requires-Dist: dask[array,distributed,dataframe] (>=2.15.0,<3.0.0); extra == "dask"
Requires-Dist: dask_ml (>=1.3.0,<2.0.0); extra == "dask"
Requires-Dist: fuzzywuzzy (>=0.18.0,<0.19.0)
Requires-Dist: ipykernel (>=5.1,<6.0)
Requires-Dist: matplotlib (>=3.1,<4.0)
Requires-Dist: matplotsoccer (>=0.0.8,<0.0.9)
Requires-Dist: numpy (>=1.18,<2.0)
Requires-Dist: pandas (>=1.0,<2.0)
Requires-Dist: paramiko (>=2.7.1,<3.0.0); extra == "dask"
Requires-Dist: python-Levenshtein (>=0.12.0,<0.13.0)
Requires-Dist: requests (>=2.23,<3.0)
Requires-Dist: scikit-learn (>=0.22.1,<0.23.0)
Requires-Dist: seaborn (>=0.10.0,<0.11.0)
Requires-Dist: socceraction (>=0.2.1,<0.3.0)
Requires-Dist: tables (>=3.6,<4.0)
Requires-Dist: understat (>=0.1.2,<0.2.0)
Requires-Dist: xgboost (>=1.0,<2.0)
Project-URL: Repository, https://github.com/probberechts/soccer_xg
